{
  "persons": [
    {
      "name": "Arto Hellas",
      "number": "040-123456",
      "id": "1"
    },
    {
      "name": "Ada Lovelace",
      "number": "39-44-5323523",
      "id": "2"
    },
    {
      "name": "Dan Abramov",
      "number": "908-7480307",
      "id": "3"
    },
    {
      "name": "Mary Poppendieck",
      "number": "908-7480307",
      "id": "4"
    },
    {
      "id": "3068",
      "name": "Testy McTestington",
      "number": "501-4832126"
    },
    {
      "id": "7eb9",
      "name": "Nathan Silva",
      "number": "908-7429999"
    },
    {
      "id": "416c",
      "name": "John John",
      "number": "420-4206969"
    }
  ]
}